esi/__init__.py
esi/_services_mixin.py
esi/connection.py
esi/cloud/__init__.py
esi/cloud/_lease.py
esi/lease/__init__.py
esi/lease/lease_service.py
esi/lease/v1/__init__.py
esi/lease/v1/_common.py
esi/lease/v1/_proxy.py
esi/lease/v1/console_auth_token.py
esi/lease/v1/event.py
esi/lease/v1/lease.py
esi/lease/v1/node.py
esi/lease/v1/offer.py
esi/lib/__init__.py
esi/lib/networks.py
esi/lib/nodes.py
esi/tests/__init__.py
esi/tests/fakes.py
esi/tests/functional/__init__.py
esi/tests/functional/lease/README.md
esi/tests/functional/lease/__init__.py
esi/tests/functional/lease/base.py
esi/tests/functional/lease/test_esi_leap_event.py
esi/tests/functional/lease/test_esi_leap_lease.py
esi/tests/functional/lease/test_esi_leap_node.py
esi/tests/functional/lease/test_esi_leap_offer.py
esi/tests/unit/__init__.py
esi/tests/unit/base.py
esi/tests/unit/utils.py
esi/tests/unit/cloud/__init__.py
esi/tests/unit/cloud/test_lease.py
esi/tests/unit/lease/__init__.py
esi/tests/unit/lease/v1/__init__.py
esi/tests/unit/lease/v1/test_console_auth_token.py
esi/tests/unit/lease/v1/test_event.py
esi/tests/unit/lease/v1/test_lease.py
esi/tests/unit/lease/v1/test_node.py
esi/tests/unit/lease/v1/test_offer.py
esi/tests/unit/lease/v1/test_proxy.py
esi/tests/unit/lib/__init__.py
esi/tests/unit/lib/test_networks.py
esi/tests/unit/lib/test_nodes.py
esisdk-1.5.0.dist-info/licenses/AUTHORS
esisdk-1.5.0.dist-info/licenses/LICENSE
esisdk-1.5.0.dist-info/METADATA
esisdk-1.5.0.dist-info/WHEEL
esisdk-1.5.0.dist-info/pbr.json
esisdk-1.5.0.dist-info/top_level.txt
esisdk-1.5.0.dist-info/RECORD
